{
  "reg_apps_cfg": [
    {
      "name": "settings.bs",
      "display": "Einstellungen",
      "version": 1,
      "author": "MCTzOCK",
      "icon": "apps/settings.bs/icon.png",
      "description": "Konfiguriere deinen PC",
      "uninstall": false,
      "desktop": true
    },
    {
      "name": "store",
      "display": "Programme",
      "version": 1,
      "author": "MCTzOCK",
      "icon": "apps/store/icon.png",
      "description": "Verwalte Programme",
      "uninstall": false,
      "desktop": true
    },
    {
      "name": "explorer.new",
      "display": "Dateien",
      "version": 1,
      "author": "MCTzOCK",
      "icon": "apps/explorer/icon.png",
      "description": "Verwalte deine Daten!",
      "uninstall": false,
      "desktop": true
    },
    {
      "name": "kalender",
      "display": "Kalender",
      "version": 1,
      "author": "_Mister_Mystic_",
      "icon": "apps/kalender/icon.png",
      "description": "Plane dein Leben bis zum Tod.",
      "uninstall": false,
      "desktop": true
    },
    {
      "name": "kontakte",
      "display": "Kontakte",
      "version": 1,
      "author": "_Mister_Mystic_",
      "icon": "apps/kontakte/icon.png",
      "description": "Speichere wichtige Menschen.",
      "uninstall": false,
      "desktop": true
    },
    {
      "name": "todo",
      "display": "Aufgaben",
      "version": 1,
      "author": "MCTzOCK",
      "icon": "apps/todo/icon.png",
      "description": "Plane deinen Tag bis in letzte Deteil.",
      "uninstall": false,
      "desktop": true
    },
    {
      "name": "radio",
      "display": "Radio",
      "version": 1,
      "author": "_Mister_Mystic_",
      "icon": "apps/radio/icon.png",
      "description": "Höre Radio!",
      "uninstall": false,
      "desktop": true
    },
    {
      "name": "clock",
      "display": "Uhr",
      "version": 1,
      "author": "MCTzOCK",
      "icon": "apps/uhr/icon.png",
      "description": "Timer, Stoppuhr, etc!",
      "uninstall": false,
      "desktop": true
    },
    {
      "name": "browser",
      "display": "Internet",
      "version": 1,
      "author": "MCTzOCK",
      "icon": "apps/browser/icon.png",
      "description": "Surfe im Internet!",
      "uninstall": false,
      "desktop": true
    },
    {
      "name": "chat",
      "display": "Chat",
      "version": 1,
      "author": "MCTzOCK",
      "icon": "apps/chat/icon.png",
      "description": "Bekomme Hilfe!",
      "uninstall": false,
      "desktop": true
    },
    {
      "name": "notizen",
      "display": "Notizen",
      "version": 1,
      "author": "_Mister_Mystic_",
      "icon": "apps/notizen/icon.png",
      "description": "Schreibe eine Notiz!",
      "uninstall": false,
      "desktop": true
    },
    {
      "name": "passwort-manager",
      "display": "Passwörter",
      "version": 1,
      "author": "_Mister_Mystic_",
      "icon": "apps/passwort-manager/icon.png",
      "description": "Speicher deine Passwörter!",
      "uninstall": false,
      "desktop": true
    },
    {
      "name": "shorts",
      "display": "Abkürzungen",
      "version": 1,
      "author": "MCTzOCK",
      "icon": "apps/shorts/icon.png",
      "description": "",
      "uninstall": false,
      "desktop": true
    },
    {
      "name": "pictures",
      "display": "Bilder",
      "version": 1,
      "author": "MCTzOCK",
      "icon": "undefined/undefinded/undefined.undefined",
      "description": "",
      "uninstall": false,
      "desktop": false
    },
    {
      "name": "pdfviewer",
      "display": "PDF-Viewer",
      "version": 1,
      "author": "MCTzOCK",
      "icon": "undefined/undefinded/undefined.undefined",
      "description": "",
      "uninstall": false,
      "desktop": false
    },
    {
      "name": "calc",
      "display": "Taschenrechner",
      "version": 1,
      "author": "SenOS Development Team",
      "icon": "apps/calc/icon.png",
      "description": "Rechne!",
      "uninstall": true,
      "desktop": true
    }
  ],
  "name": [
    "settings.bs",
    "store",
    "explorer.new",
    "kalender",
    "kontakte",
    "todo",
    "radio",
    "clock",
    "browser",
    "chat",
    "notizen",
    "passwort-manager",
    "shorts",
    "pictures",
    "pdfviewer",
    "calc"
  ]
}